readQR/__init__.py
readQR/readQR.py
readQR/wechat_artefacts/detect.caffemodel
readQR/wechat_artefacts/detect.prototxt
readQR/wechat_artefacts/sr.caffemodel
readQR/wechat_artefacts/sr.prototxt
readQR-0.1.4.8.dist-info/METADATA
readQR-0.1.4.8.dist-info/WHEEL
readQR-0.1.4.8.dist-info/top_level.txt
readQR-0.1.4.8.dist-info/RECORD
