Metadata-Version: 2.1
Name: readQR
Version: 0.1.4.8
Summary: Read QR code from image using WeChat QR code reader in OpenCV
Home-page: https://github.com/CollinsWakholi/QR_Code
Author: Collins Wakholi
Classifier: Programming Language :: Python :: 3.11
Classifier: Operating System :: OS Independent
Requires-Python: >=3.6
Requires-Dist: numpy
Requires-Dist: opencv-python
Requires-Dist: opencv-contrib-python
Requires-Dist: matplotlib
